<?xml version="1.0" encoding="utf-8" standalone="yes" ?>
<traffic_informations>
  <event>
    <id>15448416079</id>
    <type>1</type>
    <speed>50</speed>
    <quality>3</quality>
    <address>
      <zip>86316</zip>
      <city>Friedberg</city>
      <state>DE-BY</state>
      <street>Augsburger Straße</street>
      <country>DE</country>
    </address>
    <location>
      <point>
        <latitude>48.358821</latitude>
        <longitude>10.980347</longitude>
      </point>
    </location>
    <date>
      <create>2025-02-10T13:26:16+01:00</create>
      <lastuse>2025-02-10T19:09:02+01:00</lastuse>
      <lastconfirm>2025-02-10T18:09:02+01:00</lastconfirm>
    </date>
  </event>
  <event>
    <id>15449213287</id>
    <type>1</type>
    <speed>50</speed>
    <quality>3</quality>
    <address>
      <zip>86462</zip>
      <city>Langweid am Lech</city>
      <state>DE-BY</state>
      <street>Augsburger Straße</street>
      <country>DE</country>
    </address>
    <location>
      <point>
        <latitude>48.490143</latitude>
        <longitude>10.858159</longitude>
      </point>
    </location>
    <date>
      <create>2025-02-10T16:29:03+01:00</create>
      <lastuse>2025-02-10T19:15:53+01:00</lastuse>
      <lastconfirm>2025-02-10T17:15:54+01:00</lastconfirm>
    </date>
  </event>
  <event>
    <id>15449520728</id>
    <type>1</type>
    <speed>120</speed>
    <quality>3</quality>
    <address>
      <zip>86695</zip>
      <city>Allmannshofen</city>
      <state>DE-BY</state>
      <street>B2</street>
      <country>DE</country>
    </address>
    <location>
      <point>
        <latitude>48.614106</latitude>
        <longitude>10.838150</longitude>
      </point>
    </location>
    <date>
      <create>2025-02-10T17:37:17+01:00</create>
      <lastuse>2025-02-10T21:37:17+01:00</lastuse>
      <lastconfirm>2025-02-10T18:38:08+01:00</lastconfirm>
    </date>
  </event>
  <event>
    <id>15414620635</id>
    <type>7</type>
    <speed>50</speed>
    <quality>3</quality>
    <address>
      <zip>86316</zip>
      <city>Friedberg</city>
      <state>DE-BY</state>
      <street>Paartalstraße</street>
      <country>DE</country>
    </address>
    <location>
      <point>
        <latitude>48.336550</latitude>
        <longitude>11.002480</longitude>
      </point>
    </location>
    <date>
      <create>2025-02-04T10:02:04+01:00</create>
      <lastuse>2025-02-11T01:23:48+01:00</lastuse>
      <lastconfirm>2025-02-10T17:23:50+01:00</lastconfirm>
    </date>
  </event>
  <event>
    <id>15421188500</id>
    <type>7</type>
    <speed>120</speed>
    <quality>3</quality>
    <address>
      <zip>86368</zip>
      <city>Gersthofen</city>
      <state>DE-BY</state>
      <street>A8</street>
      <country>DE</country>
    </address>
    <location>
      <point>
        <latitude>48.415641</latitude>
        <longitude>10.855390</longitude>
      </point>
    </location>
    <date>
      <create>2025-02-05T13:49:29+01:00</create>
      <lastuse>2025-02-10T22:38:24+01:00</lastuse>
      <lastconfirm>2025-02-10T18:38:24+01:00</lastconfirm>
    </date>
  </event>
  <event>
    <id>15449256424</id>
    <type>20</type>
    <speed></speed>
    <quality>3</quality>
    <address>
      <zip>86316</zip>
      <city>Friedberg</city>
      <state>DE-BY</state>
      <street>La-Crosse-Ring</street>
      <country>DE</country>
    </address>
    <location>
      <point>
        <latitude>48.356423</latitude>
        <longitude>10.965317</longitude>
      </point>
    </location>
    <date>
      <create>2025-02-10T16:39:59+01:00</create>
      <lastuse>2025-02-10T18:48:22+01:00</lastuse>
      <lastconfirm>2025-02-10T17:48:23+01:00</lastconfirm>
    </date>
  </event>
  <event>
    <id>15449124801</id>
    <type>22</type>
    <speed></speed>
    <quality>3</quality>
    <address>
      <zip>86343</zip>
      <city>Königsbrunn</city>
      <state>DE-HH</state>
      <street>B17</street>
      <country>DE</country>
    </address>
    <location>
      <point>
        <latitude>48.261331</latitude>
        <longitude>10.866304</longitude>
      </point>
    </location>
    <date>
      <create>2025-02-10T16:07:19+01:00</create>
      <lastuse>2025-02-10T23:43:04+01:00</lastuse>
      <lastconfirm>2025-02-10T16:07:19+01:00</lastconfirm>
    </date>
  </event>
  <event>
    <id>15447203836</id>
    <type>22</type>
    <speed></speed>
    <quality>3</quality>
    <address>
      <zip>86343</zip>
      <city>Königsbrunn</city>
      <state>DE-HH</state>
      <street>B17</street>
      <country>DE</country>
    </address>
    <location>
      <point>
        <latitude>48.264318</latitude>
        <longitude>10.866369</longitude>
      </point>
    </location>
    <date>
      <create>2025-02-10T08:38:56+01:00</create>
      <lastuse>2025-02-10T22:16:46+01:00</lastuse>
      <lastconfirm>2025-02-10T08:38:56+01:00</lastconfirm>
    </date>
  </event>
  <event>
    <id>15363365193</id>
    <type>26</type>
    <speed></speed>
    <quality>3</quality>
    <address>
      <zip>86199</zip>
      <city>Augsburg</city>
      <state>DE-HH</state>
      <street>Lindauer Straße</street>
      <country>DE</country>
    </address>
    <location>
      <point>
        <latitude>48.332602</latitude>
        <longitude>10.866959</longitude>
      </point>
    </location>
    <date>
      <create>2025-01-25T18:59:32+01:00</create>
      <lastuse>2025-02-12T17:13:36+01:00</lastuse>
      <lastconfirm>2025-02-10T17:13:37+01:00</lastconfirm>
    </date>
  </event>
  <event>
    <id>15350243746</id>
    <type>26</type>
    <speed></speed>
    <quality>3</quality>
    <address>
      <zip>86199</zip>
      <city>Augsburg</city>
      <state>DE-HH</state>
      <street>Bahnstraße</street>
      <country>DE</country>
    </address>
    <location>
      <point>
        <latitude>48.337911</latitude>
        <longitude>10.870578</longitude>
      </point>
    </location>
    <date>
      <create>2024-12-09T13:01:11+01:00</create>
      <lastuse>2025-02-12T17:41:27+01:00</lastuse>
      <lastconfirm>2025-02-10T17:41:28+01:00</lastconfirm>
    </date>
  </event>
  <event>
    <id>15421448923</id>
    <type>26</type>
    <speed></speed>
    <quality>3</quality>
    <address>
      <zip>86199</zip>
      <city>Augsburg</city>
      <state>DE-HH</state>
      <street>Bahnstraße</street>
      <country>DE</country>
    </address>
    <location>
      <point>
        <latitude>48.337922</latitude>
        <longitude>10.869540</longitude>
      </point>
    </location>
    <date>
      <create>2025-02-05T14:47:28+01:00</create>
      <lastuse>2025-02-11T21:38:22+01:00</lastuse>
      <lastconfirm>2025-02-05T14:47:28+01:00</lastconfirm>
    </date>
  </event>
  <event>
    <id>15226877501</id>
    <type>26</type>
    <speed></speed>
    <quality>3</quality>
    <address>
      <zip>86199</zip>
      <city>Augsburg</city>
      <state>DE-HH</state>
      <street>Peter-Dörfler-Straße</street>
      <country>DE</country>
    </address>
    <location>
      <point>
        <latitude>48.348041</latitude>
        <longitude>10.880894</longitude>
      </point>
    </location>
    <date>
      <create>2024-12-29T16:25:43+01:00</create>
      <lastuse>2025-02-12T17:30:27+01:00</lastuse>
      <lastconfirm>2025-02-10T17:30:27+01:00</lastconfirm>
    </date>
  </event>
  <event>
    <id>15226634838</id>
    <type>26</type>
    <speed></speed>
    <quality>3</quality>
    <address>
      <zip>86152</zip>
      <city>Augsburg</city>
      <state>DE-HH</state>
      <street>Klinkerberg</street>
      <country>DE</country>
    </address>
    <location>
      <point>
        <latitude>48.371863</latitude>
        <longitude>10.885727</longitude>
      </point>
    </location>
    <date>
      <create>2024-12-29T15:15:11+01:00</create>
      <lastuse>2025-02-12T18:29:08+01:00</lastuse>
      <lastconfirm>2025-02-10T18:29:09+01:00</lastconfirm>
    </date>
  </event>
  <event>
    <id>15384181262</id>
    <type>26</type>
    <speed></speed>
    <quality>3</quality>
    <address>
      <zip>86153</zip>
      <city>Augsburg</city>
      <state>DE-HH</state>
      <street>Berliner Allee</street>
      <country>DE</country>
    </address>
    <location>
      <point>
        <latitude>48.375068</latitude>
        <longitude>10.914438</longitude>
      </point>
    </location>
    <date>
      <create>2025-01-29T17:57:19+01:00</create>
      <lastuse>2025-02-12T17:38:12+01:00</lastuse>
      <lastconfirm>2025-02-10T17:38:12+01:00</lastconfirm>
    </date>
  </event>
  <event>
    <id>15384689986</id>
    <type>26</type>
    <speed></speed>
    <quality>3</quality>
    <address>
      <zip>86153</zip>
      <city>Augsburg</city>
      <state>DE-HH</state>
      <street>Berliner Allee</street>
      <country>DE</country>
    </address>
    <location>
      <point>
        <latitude>48.375561</latitude>
        <longitude>10.913290</longitude>
      </point>
    </location>
    <date>
      <create>2025-01-29T19:58:24+01:00</create>
      <lastuse>2025-02-12T18:06:44+01:00</lastuse>
      <lastconfirm>2025-02-10T18:06:44+01:00</lastconfirm>
    </date>
  </event>
  <event>
    <id>15189056799</id>
    <type>26</type>
    <speed></speed>
    <quality>3</quality>
    <address>
      <zip>89420</zip>
      <city>Höchstädt an der Donau</city>
      <state>DE-HH</state>
      <street>Donauwörther Straße</street>
      <country>DE</country>
    </address>
    <location>
      <point>
        <latitude>48.617226</latitude>
        <longitude>10.567626</longitude>
      </point>
    </location>
    <date>
      <create>2024-12-21T15:13:27+01:00</create>
      <lastuse>2025-02-12T17:44:06+01:00</lastuse>
      <lastconfirm>2025-02-10T17:44:06+01:00</lastconfirm>
    </date>
  </event>
</traffic_informations>