<?xml version="1.0" encoding="utf-8" standalone="yes" ?>
<traffic_informations>
  <event>
    <id>15207243162</id>
    <type>1</type>
    <speed>70</speed>
    <quality>3</quality>
    <address>
      <zip>86167</zip>
      <city>Augsburg</city>
      <state>DE-BY</state>
      <street>Mühlhauser Straße</street>
      <country>DE</country>
    </address>
    <location>
      <point>
        <latitude>48.403329</latitude>
        <longitude>10.920511</longitude>
      </point>
    </location>
    <date>
      <create>2024-12-25T08:16:49+01:00</create>
      <lastuse>2024-12-25T13:51:39+01:00</lastuse>
      <lastconfirm>2024-12-25T11:51:40+01:00</lastconfirm>
    </date>
  </event>
  <event>
    <id>15207531764</id>
    <type>1</type>
    <speed>40</speed>
    <quality>3</quality>
    <address>
      <zip>86504</zip>
      <city>Merching</city>
      <state>DE-BY</state>
      <street>St 2380</street>
      <country>DE</country>
    </address>
    <location>
      <point>
        <latitude>48.266786</latitude>
        <longitude>10.933097</longitude>
      </point>
    </location>
    <date>
      <create>2024-12-25T10:02:53+01:00</create>
      <lastuse>2024-12-25T13:53:37+01:00</lastuse>
      <lastconfirm>2024-12-25T11:53:38+01:00</lastconfirm>
    </date>
  </event>
  <event>
    <id>15207700575</id>
    <type>1</type>
    <speed>70</speed>
    <quality>3</quality>
    <address>
      <zip>86167</zip>
      <city>Augsburg</city>
      <state>DE-BY</state>
      <street>Mühlhauser Straße</street>
      <country>DE</country>
    </address>
    <location>
      <point>
        <latitude>48.408547</latitude>
        <longitude>10.920316</longitude>
      </point>
    </location>
    <date>
      <create>2024-12-25T11:02:16+01:00</create>
      <lastuse>2024-12-25T14:02:16+01:00</lastuse>
      <lastconfirm>2024-12-25T11:48:37+01:00</lastconfirm>
    </date>
  </event>
  <event>
    <id>15207754817</id>
    <type>6</type>
    <speed></speed>
    <quality>3</quality>
    <address>
      <zip>86169</zip>
      <city>Augsburg</city>
      <state>DE-BY</state>
      <street>A8</street>
      <country>DE</country>
    </address>
    <location>
      <point>
        <latitude>48.413375</latitude>
        <longitude>10.897949</longitude>
      </point>
    </location>
    <date>
      <create>2024-12-25T11:20:33+01:00</create>
      <lastuse>2024-12-25T13:23:47+01:00</lastuse>
      <lastconfirm>2024-12-25T11:53:48+01:00</lastconfirm>
    </date>
  </event>
  <event>
    <id>15179551330</id>
    <type>7</type>
    <speed>120</speed>
    <quality>3</quality>
    <address>
      <zip>86462</zip>
      <city>Langweid am Lech</city>
      <state>DE-BY</state>
      <street>B2</street>
      <country>DE</country>
    </address>
    <location>
      <point>
        <latitude>48.492383</latitude>
        <longitude>10.860178</longitude>
      </point>
    </location>
    <date>
      <create>2024-12-19T11:35:30+01:00</create>
      <lastuse>2024-12-25T19:53:22+01:00</lastuse>
      <lastconfirm>2024-12-25T11:53:23+01:00</lastconfirm>
    </date>
  </event>
  <event>
    <id>14564025372</id>
    <type>26</type>
    <speed></speed>
    <quality>3</quality>
    <address>
      <zip>86343</zip>
      <city>Königsbrunn</city>
      <state>DE-HH</state>
      <street>Bürgermeister-Wohlfarth-Straße</street>
      <country>DE</country>
    </address>
    <location>
      <point>
        <latitude>48.272648</latitude>
        <longitude>10.889224</longitude>
      </point>
    </location>
    <date>
      <create>2024-09-30T12:37:25+02:00</create>
      <lastuse>2024-12-27T10:59:59+01:00</lastuse>
      <lastconfirm>2024-12-25T10:59:59+01:00</lastconfirm>
    </date>
  </event>
  <event>
    <id>15117413283</id>
    <type>26</type>
    <speed></speed>
    <quality>3</quality>
    <address>
      <zip>86199</zip>
      <city>Augsburg</city>
      <state>DE-HH</state>
      <street>Bahnstraße</street>
      <country>DE</country>
    </address>
    <location>
      <point>
        <latitude>48.337911</latitude>
        <longitude>10.870578</longitude>
      </point>
    </location>
    <date>
      <create>2024-12-09T13:01:11+01:00</create>
      <lastuse>2024-12-26T19:45:29+01:00</lastuse>
      <lastconfirm>2024-12-24T19:45:29+01:00</lastconfirm>
    </date>
  </event>
  <event>
    <id>14608113506</id>
    <type>26</type>
    <speed></speed>
    <quality>3</quality>
    <address>
      <zip>86152</zip>
      <city>Augsburg</city>
      <state>DE-HH</state>
      <street>Am Katzenstadel</street>
      <country>DE</country>
    </address>
    <location>
      <point>
        <latitude>48.375379</latitude>
        <longitude>10.888003</longitude>
      </point>
    </location>
    <date>
      <create>2024-10-07T08:31:25+02:00</create>
      <lastuse>2024-12-25T12:13:44+01:00</lastuse>
      <lastconfirm>2024-10-07T08:31:25+02:00</lastconfirm>
    </date>
  </event>
  <event>
    <id>15189056799</id>
    <type>26</type>
    <speed></speed>
    <quality>3</quality>
    <address>
      <zip>89420</zip>
      <city>Höchstädt an der Donau</city>
      <state>DE-HH</state>
      <street>Donauwörther Straße</street>
      <country>DE</country>
    </address>
    <location>
      <point>
        <latitude>48.617226</latitude>
        <longitude>10.567626</longitude>
      </point>
    </location>
    <date>
      <create>2024-12-21T15:13:27+01:00</create>
      <lastuse>2024-12-27T03:29:44+01:00</lastuse>
      <lastconfirm>2024-12-25T03:29:45+01:00</lastconfirm>
    </date>
  </event>
</traffic_informations>