<?xml version="1.0" encoding="utf-8" standalone="yes" ?>
<traffic_informations>
  <event>
    <id>15176334382</id>
    <type>1</type>
    <speed>50</speed>
    <quality>2</quality>
    <address>
      <zip>86343</zip>
      <city>Königsbrunn</city>
      <state>DE-BY</state>
      <street>Landsberger Straße</street>
      <country>DE</country>
    </address>
    <location>
      <point>
        <latitude>48.257270</latitude>
        <longitude>10.882587</longitude>
      </point>
    </location>
    <date>
      <create>2024-12-19T11:38:22+01:00</create>
      <lastuse>2024-12-19T14:12:41+01:00</lastuse>
      <lastconfirm>2024-12-19T12:12:42+01:00</lastconfirm>
    </date>
  </event>
  <event>
    <id>15176334385</id>
    <type>1</type>
    <speed>60</speed>
    <quality>3</quality>
    <address>
      <zip>86153</zip>
      <city>Augsburg</city>
      <state>DE-BY</state>
      <street>Nagahama-Allee</street>
      <country>DE</country>
    </address>
    <location>
      <point>
        <latitude>48.365734</latitude>
        <longitude>10.913616</longitude>
      </point>
    </location>
    <date>
      <create>2024-12-19T11:38:22+01:00</create>
      <lastuse>2024-12-19T14:24:55+01:00</lastuse>
      <lastconfirm>2024-12-19T12:24:56+01:00</lastconfirm>
    </date>
  </event>
  <event>
    <id>15176238915</id>
    <type>1</type>
    <speed>30</speed>
    <quality>2</quality>
    <address>
      <zip>86152</zip>
      <city>Augsburg</city>
      <state>DE-BY</state>
      <street>Holzbachstraße</street>
      <country>DE</country>
    </address>
    <location>
      <point>
        <latitude>48.372638</latitude>
        <longitude>10.879985</longitude>
      </point>
    </location>
    <date>
      <create>2024-12-19T11:17:24+01:00</create>
      <lastuse>2024-12-19T13:54:53+01:00</lastuse>
      <lastconfirm>2024-12-19T11:54:54+01:00</lastconfirm>
    </date>
  </event>
  <event>
    <id>15175662187</id>
    <type>1</type>
    <speed>30</speed>
    <quality>3</quality>
    <address>
      <zip>86356</zip>
      <city>Neusäß</city>
      <state>DE-BY</state>
      <street>Westheimer Straße</street>
      <country>DE</country>
    </address>
    <location>
      <point>
        <latitude>48.387648</latitude>
        <longitude>10.826228</longitude>
      </point>
    </location>
    <date>
      <create>2024-12-19T09:09:07+01:00</create>
      <lastuse>2024-12-19T13:07:12+01:00</lastuse>
      <lastconfirm>2024-12-19T11:07:12+01:00</lastconfirm>
    </date>
  </event>
  <event>
    <id>15175949514</id>
    <type>6</type>
    <speed></speed>
    <quality>3</quality>
    <address>
      <zip>86169</zip>
      <city>Augsburg</city>
      <state>DE-BY</state>
      <street>A8</street>
      <country>DE</country>
    </address>
    <location>
      <point>
        <latitude>48.413767</latitude>
        <longitude>10.894703</longitude>
      </point>
    </location>
    <date>
      <create>2024-12-19T10:13:23+01:00</create>
      <lastuse>2024-12-19T14:13:23+01:00</lastuse>
      <lastconfirm>2024-12-19T12:25:34+01:00</lastconfirm>
    </date>
  </event>
  <event>
    <id>15175097840</id>
    <type>1</type>
    <speed>120</speed>
    <quality>3</quality>
    <address>
      <zip>86368</zip>
      <city>Gersthofen</city>
      <state>DE-BY</state>
      <street>A8</street>
      <country>DE</country>
    </address>
    <location>
      <point>
        <latitude>48.416983</latitude>
        <longitude>10.839721</longitude>
      </point>
    </location>
    <date>
      <create>2024-12-19T06:53:15+01:00</create>
      <lastuse>2024-12-19T14:08:41+01:00</lastuse>
      <lastconfirm>2024-12-19T12:23:41+01:00</lastconfirm>
    </date>
  </event>
  <event>
    <id>15176314274</id>
    <type>1</type>
    <speed>120</speed>
    <quality>2</quality>
    <address>
      <zip>86462</zip>
      <city>Langweid am Lech</city>
      <state>DE-BY</state>
      <street>B2</street>
      <country>DE</country>
    </address>
    <location>
      <point>
        <latitude>48.487344</latitude>
        <longitude>10.861803</longitude>
      </point>
    </location>
    <date>
      <create>2024-12-19T11:34:05+01:00</create>
      <lastuse>2024-12-19T13:53:18+01:00</lastuse>
      <lastconfirm>2024-12-19T12:23:19+01:00</lastconfirm>
    </date>
  </event>
  <event>
    <id>15176324854</id>
    <type>1</type>
    <speed>120</speed>
    <quality>3</quality>
    <address>
      <zip>86462</zip>
      <city>Langweid am Lech</city>
      <state>DE-BY</state>
      <street>B2</street>
      <country>DE</country>
    </address>
    <location>
      <point>
        <latitude>48.492383</latitude>
        <longitude>10.860178</longitude>
      </point>
    </location>
    <date>
      <create>2024-12-19T11:35:30+01:00</create>
      <lastuse>2024-12-19T14:25:33+01:00</lastuse>
      <lastconfirm>2024-12-19T12:25:34+01:00</lastconfirm>
    </date>
  </event>
  <event>
    <id>15164013055</id>
    <type>7</type>
    <speed>20</speed>
    <quality>3</quality>
    <address>
      <zip>86343</zip>
      <city>Königsbrunn</city>
      <state>DE-HH</state>
      <street>Bürgermeister-Wohlfarth-Straße</street>
      <country>DE</country>
    </address>
    <location>
      <point>
        <latitude>48.268806</latitude>
        <longitude>10.887591</longitude>
      </point>
    </location>
    <date>
      <create>2024-12-17T10:58:21+01:00</create>
      <lastuse>2024-12-19T19:59:19+01:00</lastuse>
      <lastconfirm>2024-12-19T11:59:20+01:00</lastconfirm>
    </date>
  </event>
  <event>
    <id>14564025372</id>
    <type>26</type>
    <speed></speed>
    <quality>3</quality>
    <address>
      <zip>86343</zip>
      <city>Königsbrunn</city>
      <state>DE-HH</state>
      <street>Bürgermeister-Wohlfarth-Straße</street>
      <country>DE</country>
    </address>
    <location>
      <point>
        <latitude>48.272648</latitude>
        <longitude>10.889224</longitude>
      </point>
    </location>
    <date>
      <create>2024-09-30T12:37:25+02:00</create>
      <lastuse>2024-12-21T10:02:38+01:00</lastuse>
      <lastconfirm>2024-12-19T10:02:38+01:00</lastconfirm>
    </date>
  </event>
  <event>
    <id>15117413283</id>
    <type>26</type>
    <speed></speed>
    <quality>3</quality>
    <address>
      <zip>86199</zip>
      <city>Augsburg</city>
      <state>DE-HH</state>
      <street>Bahnstraße</street>
      <country>DE</country>
    </address>
    <location>
      <point>
        <latitude>48.337911</latitude>
        <longitude>10.870578</longitude>
      </point>
    </location>
    <date>
      <create>2024-12-09T13:01:11+01:00</create>
      <lastuse>2024-12-21T12:14:21+01:00</lastuse>
      <lastconfirm>2024-12-19T12:14:21+01:00</lastconfirm>
    </date>
  </event>
  <event>
    <id>14589547055</id>
    <type>26</type>
    <speed></speed>
    <quality>2</quality>
    <address>
      <zip>86199</zip>
      <city>Augsburg</city>
      <state>DE-HH</state>
      <street>Bergstraße</street>
      <country>DE</country>
    </address>
    <location>
      <point>
        <latitude>48.350260</latitude>
        <longitude>10.876473</longitude>
      </point>
    </location>
    <date>
      <create>2024-10-04T10:46:26+02:00</create>
      <lastuse>2024-12-21T11:15:55+01:00</lastuse>
      <lastconfirm>2024-12-19T11:15:55+01:00</lastconfirm>
    </date>
  </event>
  <event>
    <id>15169324649</id>
    <type>26</type>
    <speed></speed>
    <quality>3</quality>
    <address>
      <zip>86199</zip>
      <city>Augsburg</city>
      <state>DE-HH</state>
      <street>Depotstraße</street>
      <country>DE</country>
    </address>
    <location>
      <point>
        <latitude>48.350329</latitude>
        <longitude>10.882388</longitude>
      </point>
    </location>
    <date>
      <create>2024-12-05T07:51:53+01:00</create>
      <lastuse>2024-12-25T02:02:07+01:00</lastuse>
      <lastconfirm>2024-12-17T17:05:02+01:00</lastconfirm>
    </date>
  </event>
  <event>
    <id>15163147931</id>
    <type>26</type>
    <speed></speed>
    <quality>3</quality>
    <address>
      <zip>86391</zip>
      <city>Stadtbergen</city>
      <state>DE-HH</state>
      <street>Augsburger Straße</street>
      <country>DE</country>
    </address>
    <location>
      <point>
        <latitude>48.350648</latitude>
        <longitude>10.848411</longitude>
      </point>
    </location>
    <date>
      <create>2024-12-17T07:45:46+01:00</create>
      <lastuse>2024-12-21T11:33:50+01:00</lastuse>
      <lastconfirm>2024-12-19T11:33:51+01:00</lastconfirm>
    </date>
  </event>
  <event>
    <id>14608113506</id>
    <type>26</type>
    <speed></speed>
    <quality>2</quality>
    <address>
      <zip>86152</zip>
      <city>Augsburg</city>
      <state>DE-HH</state>
      <street>Am Katzenstadel</street>
      <country>DE</country>
    </address>
    <location>
      <point>
        <latitude>48.375379</latitude>
        <longitude>10.888003</longitude>
      </point>
    </location>
    <date>
      <create>2024-10-07T08:31:25+02:00</create>
      <lastuse>2024-12-21T08:26:35+01:00</lastuse>
      <lastconfirm>2024-12-19T08:26:35+01:00</lastconfirm>
    </date>
  </event>
  <event>
    <id>14355299416</id>
    <type>26</type>
    <speed></speed>
    <quality>2</quality>
    <address>
      <zip>86156</zip>
      <city>Augsburg</city>
      <state>DE-HH</state>
      <street>Holzweg</street>
      <country>DE</country>
    </address>
    <location>
      <point>
        <latitude>48.391450</latitude>
        <longitude>10.857411</longitude>
      </point>
    </location>
    <date>
      <create>2024-08-30T13:20:03+02:00</create>
      <lastuse>2024-12-21T03:38:17+01:00</lastuse>
      <lastconfirm>2024-08-30T13:20:03+02:00</lastconfirm>
    </date>
  </event>
  <event>
    <id>14822107601</id>
    <type>26</type>
    <speed></speed>
    <quality>3</quality>
    <address>
      <zip>89420</zip>
      <city>Höchstädt an der Donau</city>
      <state>DE-HH</state>
      <street>Donauwörther Straße</street>
      <country>DE</country>
    </address>
    <location>
      <point>
        <latitude>48.619277</latitude>
        <longitude>10.569255</longitude>
      </point>
    </location>
    <date>
      <create>2024-11-09T07:54:00+01:00</create>
      <lastuse>2024-12-21T08:24:54+01:00</lastuse>
      <lastconfirm>2024-12-19T08:24:54+01:00</lastconfirm>
    </date>
  </event>
</traffic_informations>