<?xml version="1.0" encoding="utf-8" standalone="yes" ?>
<traffic_informations>
  <event>
    <id>15539042616</id>
    <type>1</type>
    <speed>120</speed>
    <quality>3</quality>
    <address>
      <zip>86507</zip>
      <city>Oberottmarshausen</city>
      <state>DE-BY</state>
      <street>B17</street>
      <country>DE</country>
    </address>
    <location>
      <point>
        <latitude>48.227692</latitude>
        <longitude>10.866777</longitude>
      </point>
    </location>
    <date>
      <create>2025-02-26T15:56:37+01:00</create>
      <lastuse>2025-02-26T21:26:44+01:00</lastuse>
      <lastconfirm>2025-02-26T19:26:44+01:00</lastconfirm>
    </date>
  </event>
  <event>
    <id>15538429727</id>
    <type>1</type>
    <speed>100</speed>
    <quality>3</quality>
    <address>
      <zip>86453</zip>
      <city>Dasing</city>
      <state>DE-BY</state>
      <street>B300</street>
      <country>DE</country>
    </address>
    <location>
      <point>
        <latitude>48.388304</latitude>
        <longitude>11.032288</longitude>
      </point>
    </location>
    <date>
      <create>2025-02-26T13:47:58+01:00</create>
      <lastuse>2025-02-26T21:19:01+01:00</lastuse>
      <lastconfirm>2025-02-26T19:19:03+01:00</lastconfirm>
    </date>
  </event>
  <event>
    <id>15539420659</id>
    <type>1</type>
    <speed>100</speed>
    <quality>3</quality>
    <address>
      <zip>86551</zip>
      <city>Aichach</city>
      <state>DE-BY</state>
      <street>B300</street>
      <country>DE</country>
    </address>
    <location>
      <point>
        <latitude>48.435264</latitude>
        <longitude>11.125714</longitude>
      </point>
    </location>
    <date>
      <create>2025-02-26T17:14:01+01:00</create>
      <lastuse>2025-02-26T21:25:42+01:00</lastuse>
      <lastconfirm>2025-02-26T19:25:42+01:00</lastconfirm>
    </date>
  </event>
  <event>
    <id>15536621067</id>
    <type>7</type>
    <speed>50</speed>
    <quality>2</quality>
    <address>
      <zip>86492</zip>
      <city>Egling an der Paar</city>
      <state>DE-BY</state>
      <street>Badstraße</street>
      <country>DE</country>
    </address>
    <location>
      <point>
        <latitude>48.186537</latitude>
        <longitude>10.986287</longitude>
      </point>
    </location>
    <date>
      <create>2025-02-26T07:04:05+01:00</create>
      <lastuse>2025-02-26T15:59:26+01:00</lastuse>
      <lastconfirm>2025-02-26T09:59:26+01:00</lastconfirm>
    </date>
  </event>
  <event>
    <id>15538155347</id>
    <type>7</type>
    <speed>30</speed>
    <quality>3</quality>
    <address>
      <zip>86343</zip>
      <city>Königsbrunn</city>
      <state>DE-BY</state>
      <street>Egerländer Straße</street>
      <country>DE</country>
    </address>
    <location>
      <point>
        <latitude>48.272604</latitude>
        <longitude>10.896177</longitude>
      </point>
    </location>
    <date>
      <create>2025-02-26T12:49:23+01:00</create>
      <lastuse>2025-02-27T03:02:46+01:00</lastuse>
      <lastconfirm>2025-02-26T19:02:47+01:00</lastconfirm>
    </date>
  </event>
  <event>
    <id>15532003121</id>
    <type>7</type>
    <speed>30</speed>
    <quality>3</quality>
    <address>
      <zip>86316</zip>
      <city>Friedberg</city>
      <state>DE-BY</state>
      <street>Haberskircher Straße</street>
      <country>DE</country>
    </address>
    <location>
      <point>
        <latitude>48.392232</latitude>
        <longitude>10.977254</longitude>
      </point>
    </location>
    <date>
      <create>2025-02-25T11:51:49+01:00</create>
      <lastuse>2025-02-26T22:12:37+01:00</lastuse>
      <lastconfirm>2025-02-26T14:12:38+01:00</lastconfirm>
    </date>
  </event>
  <event>
    <id>15539887463</id>
    <type>29</type>
    <speed></speed>
    <quality>3</quality>
    <address>
      <zip>86169</zip>
      <city>Friedberg</city>
      <state>DE-BY</state>
      <street>A8</street>
      <country>DE</country>
    </address>
    <location>
      <point>
        <latitude>48.407635</latitude>
        <longitude>10.933875</longitude>
      </point>
    </location>
    <date>
      <create>2025-02-26T18:51:17+01:00</create>
      <lastuse>2025-02-26T21:27:25+01:00</lastuse>
      <lastconfirm>2025-02-26T19:27:25+01:00</lastconfirm>
    </date>
  </event>
  <event>
    <id>15539974789</id>
    <type>23</type>
    <speed></speed>
    <quality>2</quality>
    <address>
      <zip>86169</zip>
      <city>Friedberg</city>
      <state>DE-BY</state>
      <street>A8</street>
      <country>DE</country>
    </address>
    <location>
      <point>
        <latitude>48.407104</latitude>
        <longitude>10.937318</longitude>
      </point>
    </location>
    <date>
      <create>2025-02-26T19:10:36+01:00</create>
      <lastuse>2025-02-26T19:57:20+01:00</lastuse>
      <lastconfirm>2025-02-26T19:27:21+01:00</lastconfirm>
    </date>
  </event>
  <event>
    <id>15363365193</id>
    <type>26</type>
    <speed></speed>
    <quality>3</quality>
    <address>
      <zip>86199</zip>
      <city>Augsburg</city>
      <state>DE-HH</state>
      <street>Lindauer Straße</street>
      <country>DE</country>
    </address>
    <location>
      <point>
        <latitude>48.332602</latitude>
        <longitude>10.866959</longitude>
      </point>
    </location>
    <date>
      <create>2025-01-25T18:59:32+01:00</create>
      <lastuse>2025-02-28T17:16:10+01:00</lastuse>
      <lastconfirm>2025-02-26T17:16:10+01:00</lastconfirm>
    </date>
  </event>
  <event>
    <id>15350243746</id>
    <type>26</type>
    <speed></speed>
    <quality>3</quality>
    <address>
      <zip>86199</zip>
      <city>Augsburg</city>
      <state>DE-HH</state>
      <street>Bahnstraße</street>
      <country>DE</country>
    </address>
    <location>
      <point>
        <latitude>48.337911</latitude>
        <longitude>10.870578</longitude>
      </point>
    </location>
    <date>
      <create>2024-12-09T13:01:11+01:00</create>
      <lastuse>2025-02-27T23:46:44+01:00</lastuse>
      <lastconfirm>2024-12-09T13:01:11+01:00</lastconfirm>
    </date>
  </event>
  <event>
    <id>15421448923</id>
    <type>26</type>
    <speed></speed>
    <quality>3</quality>
    <address>
      <zip>86199</zip>
      <city>Augsburg</city>
      <state>DE-HH</state>
      <street>Bahnstraße</street>
      <country>DE</country>
    </address>
    <location>
      <point>
        <latitude>48.337922</latitude>
        <longitude>10.869540</longitude>
      </point>
    </location>
    <date>
      <create>2025-02-05T14:47:28+01:00</create>
      <lastuse>2025-02-28T17:05:03+01:00</lastuse>
      <lastconfirm>2025-02-26T17:05:03+01:00</lastconfirm>
    </date>
  </event>
  <event>
    <id>15453973286</id>
    <type>26</type>
    <speed></speed>
    <quality>3</quality>
    <address>
      <zip>86199</zip>
      <city>Augsburg</city>
      <state>DE-HH</state>
      <street>Butzstraße</street>
      <country>DE</country>
    </address>
    <location>
      <point>
        <latitude>48.342059</latitude>
        <longitude>10.868369</longitude>
      </point>
    </location>
    <date>
      <create>2025-02-11T12:58:46+01:00</create>
      <lastuse>2025-02-28T17:54:38+01:00</lastuse>
      <lastconfirm>2025-02-26T17:54:40+01:00</lastconfirm>
    </date>
  </event>
  <event>
    <id>15226877501</id>
    <type>26</type>
    <speed></speed>
    <quality>3</quality>
    <address>
      <zip>86199</zip>
      <city>Augsburg</city>
      <state>DE-HH</state>
      <street>Peter-Dörfler-Straße</street>
      <country>DE</country>
    </address>
    <location>
      <point>
        <latitude>48.348041</latitude>
        <longitude>10.880894</longitude>
      </point>
    </location>
    <date>
      <create>2024-12-29T16:25:43+01:00</create>
      <lastuse>2025-02-28T17:15:25+01:00</lastuse>
      <lastconfirm>2025-02-26T17:15:25+01:00</lastconfirm>
    </date>
  </event>
  <event>
    <id>15226634838</id>
    <type>26</type>
    <speed></speed>
    <quality>3</quality>
    <address>
      <zip>86152</zip>
      <city>Augsburg</city>
      <state>DE-HH</state>
      <street>Klinkerberg</street>
      <country>DE</country>
    </address>
    <location>
      <point>
        <latitude>48.371863</latitude>
        <longitude>10.885727</longitude>
      </point>
    </location>
    <date>
      <create>2024-12-29T15:15:11+01:00</create>
      <lastuse>2025-02-28T19:01:57+01:00</lastuse>
      <lastconfirm>2025-02-26T19:01:57+01:00</lastconfirm>
    </date>
  </event>
  <event>
    <id>15384181262</id>
    <type>26</type>
    <speed></speed>
    <quality>3</quality>
    <address>
      <zip>86153</zip>
      <city>Augsburg</city>
      <state>DE-HH</state>
      <street>Berliner Allee</street>
      <country>DE</country>
    </address>
    <location>
      <point>
        <latitude>48.375068</latitude>
        <longitude>10.914438</longitude>
      </point>
    </location>
    <date>
      <create>2025-01-29T17:57:19+01:00</create>
      <lastuse>2025-02-28T18:41:49+01:00</lastuse>
      <lastconfirm>2025-02-26T18:41:49+01:00</lastconfirm>
    </date>
  </event>
  <event>
    <id>15384689986</id>
    <type>26</type>
    <speed></speed>
    <quality>3</quality>
    <address>
      <zip>86153</zip>
      <city>Augsburg</city>
      <state>DE-HH</state>
      <street>Berliner Allee</street>
      <country>DE</country>
    </address>
    <location>
      <point>
        <latitude>48.375561</latitude>
        <longitude>10.913290</longitude>
      </point>
    </location>
    <date>
      <create>2025-01-29T19:58:24+01:00</create>
      <lastuse>2025-02-28T18:53:44+01:00</lastuse>
      <lastconfirm>2025-02-26T18:53:46+01:00</lastconfirm>
    </date>
  </event>
  <event>
    <id>15538322419</id>
    <type>22</type>
    <speed></speed>
    <quality>2</quality>
    <address>
      <zip>86153</zip>
      <city>Augsburg</city>
      <state>DE-HH</state>
      <street>Berliner Allee</street>
      <country>DE</country>
    </address>
    <location>
      <point>
        <latitude>48.381007</latitude>
        <longitude>10.903010</longitude>
      </point>
    </location>
    <date>
      <create>2025-02-26T13:21:35+01:00</create>
      <lastuse>2025-02-27T02:51:54+01:00</lastuse>
      <lastconfirm>2025-02-26T18:51:55+01:00</lastconfirm>
    </date>
  </event>
  <event>
    <id>15189056799</id>
    <type>26</type>
    <speed></speed>
    <quality>3</quality>
    <address>
      <zip>89420</zip>
      <city>Höchstädt an der Donau</city>
      <state>DE-HH</state>
      <street>Donauwörther Straße</street>
      <country>DE</country>
    </address>
    <location>
      <point>
        <latitude>48.617226</latitude>
        <longitude>10.567626</longitude>
      </point>
    </location>
    <date>
      <create>2024-12-21T15:13:27+01:00</create>
      <lastuse>2025-02-28T18:10:13+01:00</lastuse>
      <lastconfirm>2025-02-26T18:10:14+01:00</lastconfirm>
    </date>
  </event>
</traffic_informations>